sheetwhat/Range.py
sheetwhat/State.py
sheetwhat/Test.py
sheetwhat/__init__.py
sheetwhat/sct_context.py
sheetwhat/sct_syntax.py
sheetwhat/selectors.py
sheetwhat/test_exercise.py
sheetwhat/utils.py
sheetwhat/checks/__init__.py
sheetwhat/checks/check_chart.py
sheetwhat/checks/check_funcs.py
sheetwhat/checks/has_equal_conditional_formats.py
sheetwhat/checks/has_equal_data_validation.py
sheetwhat/checks/has_equal_number_format.py
sheetwhat/checks/has_equal_pivot.py
sheetwhat-0.6.0.dist-info/licenses/LICENSE
sheetwhat-0.6.0.dist-info/METADATA
sheetwhat-0.6.0.dist-info/WHEEL
sheetwhat-0.6.0.dist-info/top_level.txt
sheetwhat-0.6.0.dist-info/RECORD
