Metadata-Version: 2.4
Name: sheetwhat
Version: 0.6.0
Summary: Submission correctness tests for spreadsheets
Home-page: https://github.com/datacamp/sheetwhat
Author: Vincent Vankrunkelsven
Author-email: vincent@datacamp.com
Maintainer: Jeroen Hermans
Maintainer-email: content-engineering@datacamp.com
Classifier: Programming Language :: Python :: 3
Classifier: License :: OSI Approved :: GNU Affero General Public License v3
Classifier: Operating System :: OS Independent
License-File: LICENSE
Requires-Dist: protowhat~=2.3.1
Requires-Dist: glom~=18.3.1
Dynamic: author
Dynamic: author-email
Dynamic: classifier
Dynamic: description
Dynamic: description-content-type
Dynamic: home-page
Dynamic: license-file
Dynamic: maintainer
Dynamic: maintainer-email
Dynamic: requires-dist
Dynamic: summary
